fastapi_doctor/__init__.py
fastapi_doctor/__main__.py
fastapi_doctor/doctor.py
fastapi_doctor/config/__init__.py
fastapi_doctor/config/project_config.py
fastapi_doctor/generators/__init__.py
fastapi_doctor/generators/file_writer.py
fastapi_doctor/generators/project_generator.py
fastapi_doctor/templates/__init__.py
fastapi_doctor/templates/api_templates.py
fastapi_doctor/templates/core_templates.py
fastapi_doctor/templates/db_templates.py
fastapi_doctor/templates/frontend_templates.py
fastapi_doctor/templates/middleware_templates.py
fastapi_doctor/templates/misc_templates.py
fastapi_doctor-0.1.0.dist-info/licenses/LICENSE.txt
fastapi_doctor-0.1.0.dist-info/METADATA
fastapi_doctor-0.1.0.dist-info/WHEEL
fastapi_doctor-0.1.0.dist-info/entry_points.txt
fastapi_doctor-0.1.0.dist-info/top_level.txt
fastapi_doctor-0.1.0.dist-info/RECORD
