Metadata-Version: 2.4
Name: fastapi_doctor
Version: 0.1.0
Summary: Scaffold your fastapi project structure easily
Author-email: Arnab Gupta <arnab95gupta@gmail.com>
Maintainer-email: Arnab Gupta <arnab95gupta@gmail.com>
License: Copyright 2025 Arnab Gupta
Project-URL: Homepage, https://github.com/r3Vibe/fastapi_doctor
Project-URL: Documentation, https://github.com/r3Vibe/fastapi_doctor/README.md
Keywords: FastAPI,Scaffolding,Project Structure,Project Generation,Project Creation,Project Initialization,Project Setup,Project Configuration
Classifier: Programming Language :: Python :: 3.12
Classifier: Programming Language :: Python :: Implementation :: CPython
Classifier: License :: OSI Approved :: BSD License
Classifier: Intended Audience :: Developers
Classifier: Operating System :: POSIX :: Linux
Classifier: Operating System :: Microsoft :: Windows
Classifier: Operating System :: MacOS
Classifier: Operating System :: MacOS :: MacOS X
Requires-Python: >=3.12
License-File: LICENSE.txt
Requires-Dist: build>=1.3.0
Requires-Dist: twine>=6.2.0
Requires-Dist: typer>=0.21.0
Dynamic: license-file
